MANIFEST.in
README.md
setup.py
cryptorito/__init__.py
cryptorito/cli.py
cryptorito/version
cryptorito.egg-info/PKG-INFO
cryptorito.egg-info/SOURCES.txt
cryptorito.egg-info/dependency_links.txt
cryptorito.egg-info/requires.txt
cryptorito.egg-info/top_level.txt