Metadata-Version: 1.0
Name: cryptorito
Version: 0.6.3
Summary: Very lightweight wrapper around GPG2 and Keybase
Home-page: https://github.com/autodesk/cryptorito
Author: Jonathan Freedman
Author-email: jonathan.freedman@autodesk.com
License: MIT
Platform: UNKNOWN
